backports/__init__.py
backports/tempfile.py
backports.tempfile-1.0rc1.dist-info/DESCRIPTION.rst
backports.tempfile-1.0rc1.dist-info/METADATA
backports.tempfile-1.0rc1.dist-info/RECORD
backports.tempfile-1.0rc1.dist-info/WHEEL
backports.tempfile-1.0rc1.dist-info/metadata.json
backports.tempfile-1.0rc1.dist-info/top_level.txt
