Metadata-Version: 1.1
Name: backports.tempfile
Version: 1.0rc1
Summary: Backport of new features in Python's tempfile module
Home-page: https://github.com/pjdelport/backports.tempfile
Author: Piët Delport
Author-email: pjdelport@gmail.com
License: Python Software Foundation License
Platform: UNKNOWN
Classifier: Development Status :: 6 - Mature
Classifier: Intended Audience :: Developers
Classifier: License :: OSI Approved :: Python Software Foundation License
Classifier: Programming Language :: Python :: 2
Classifier: Programming Language :: Python :: 2.7
Classifier: Programming Language :: Python :: 3
Classifier: Programming Language :: Python :: 3.4
Classifier: Programming Language :: Python :: 3.5
Classifier: Topic :: Software Development :: Libraries :: Python Modules
